README.md
setup.cfg
setup.py
Plot_Library/__init__.py
Plot_Library/acquire_data.py
Plot_Library/plot_data.py
macroplots.egg-info/PKG-INFO
macroplots.egg-info/SOURCES.txt
macroplots.egg-info/dependency_links.txt
macroplots.egg-info/requires.txt
macroplots.egg-info/top_level.txt