Metadata-Version: 2.1
Name: macroplots
Version: 2.0.4
Summary: This is my first module
Home-page: https://github.com/IzyGolstein
Author: Izy_Golstein
Author-email: osipovaajr@gmail.com
Project-URL: Documentation, https://github.com/IzyGolstein
Keywords: example python
Classifier: Programming Language :: Python :: 3.11
Classifier: License :: OSI Approved :: MIT License
Classifier: Operating System :: OS Independent
Requires-Python: >=3.7
